rai/__init__.py
rai/__main__.py
rai/_cli/__init__.py
rai/_cli/_paths.py
rai/_cli/docs.py
rai/_cli/propagate.py
rai/_version.py
rai/dicom/__init__.py
rai/dicom/append.py
rai/dicom/typing.py
rai/dicom/uid.py
rai/mask/__init__.py
rai/mask/convert.py
rai/mask/test_convert.py
rai/mask/test_figures/edge-of-mask.png
rai/mask/test_figures/offset-ellipse.png
rai/mask/test_figures/right-angle-triangle.png
rai/mask/test_figures/two-small-abutting-circles.png
rai/metrics/__init__.py
rai/metrics/dice.py
rai/metrics/test_dice.py
rai/py.typed
rai-0.1.3.dist-info/entry_points.txt
rai-0.1.3.dist-info/LICENSE
rai-0.1.3.dist-info/WHEEL
rai-0.1.3.dist-info/METADATA
rai-0.1.3.dist-info/RECORD
