Metadata-Version: 2.1
Name: rai
Version: 0.1.3
Summary: AI assisted treatments accessible to all
Home-page: https://radiotherapy.ai
License: AGPL-3.0-or-later
Author: Simon Biggs
Author-email: simon.biggs@radiotherapy.ai
Requires-Python: >=3.9,<3.12
Classifier: Development Status :: 4 - Beta
Classifier: Intended Audience :: Healthcare Industry
Classifier: Intended Audience :: Science/Research
Classifier: License :: OSI Approved :: GNU Affero General Public License v3 or later (AGPLv3+)
Classifier: Programming Language :: Python :: 3
Classifier: Programming Language :: Python :: 3.9
Classifier: Programming Language :: Python :: 3.10
Classifier: Topic :: Scientific/Engineering :: Medical Science Apps.
Classifier: Topic :: Scientific/Engineering :: Physics
Requires-Dist: click
Requires-Dist: numpy
Requires-Dist: pydicom
Requires-Dist: scikit-image
Requires-Dist: scipy
Requires-Dist: shapely
Project-URL: Documentation, https://docs.radiotherapy.ai
Project-URL: Repository, https://github.com/RadiotherapyAI/rai
